{
    "$schema": "http://json-schema.org/draft-04/schema#",
    "id": "#/definitions/description",
    "description": "A Description can be a raw text, or be an object, which holds the description along with its format.",
    "oneOf": [
        {
            "type": "object",
            "title": "Description",
            "properties": {
                "content": {
                    "type": "string",
                    "description": "The content of the description goes here, as a raw string."
                },
                "type": {
                    "type": "string",
                    "description": "Holds the mime type of the raw description content. E.g: 'text/markdown' or 'text/html'.\nThe type is used to correctly render the description when generating documentation, or in the Postman app."
                },
                "version": {
                    "description": "Description can have versions associated with it, which should be put in this property."
                }
            }
        },
        {
            "type": "string"
        }
    ]
}
